odoo/addons/project_custom_info/README.rst
odoo/addons/project_custom_info/__init__.py
odoo/addons/project_custom_info/__manifest__.py
odoo/addons/project_custom_info/i18n/es.po
odoo/addons/project_custom_info/i18n/it.po
odoo/addons/project_custom_info/i18n/project_custom_info.pot
odoo/addons/project_custom_info/models/__init__.py
odoo/addons/project_custom_info/models/project_project.py
odoo/addons/project_custom_info/readme/CONTRIBUTORS.rst
odoo/addons/project_custom_info/readme/DESCRIPTION.rst
odoo/addons/project_custom_info/readme/USAGE.rst
odoo/addons/project_custom_info/static/description/icon.png
odoo/addons/project_custom_info/static/description/index.html
odoo/addons/project_custom_info/views/project_project_view.xml
odoo12_addon_project_custom_info-12.0.2.0.0.dist-info/METADATA
odoo12_addon_project_custom_info-12.0.2.0.0.dist-info/WHEEL
odoo12_addon_project_custom_info-12.0.2.0.0.dist-info/top_level.txt
odoo12_addon_project_custom_info-12.0.2.0.0.dist-info/RECORD
